MANIFEST.in
README.rst
bilateral_filter_layer.py
example_filter.py
example_optimization.py
gradcheck.py
setup.py
bilateralfilter_torch.egg-info/PKG-INFO
bilateralfilter_torch.egg-info/SOURCES.txt
bilateralfilter_torch.egg-info/dependency_links.txt
bilateralfilter_torch.egg-info/top_level.txt
csrc/bf_layer_cpu_backward.cpp
csrc/bf_layer_cpu_forward.cpp
csrc/bf_layer_gpu_backward.cu
csrc/bf_layer_gpu_forward.cu
csrc/bilateral.h
csrc/bilateralfilter_cpu.cpp
csrc/bilateralfilter_gpu.cu
utils/common_utils.h
utils/cuda_error_check.h
utils/meta_macros.h
utils/resample_utils.h
utils/tensor_description.h