Metadata-Version: 2.1
Name: bilateralfilter-torch
Version: 1.1.0
Summary: Trainable Bilateral Filter Layer (PyTorch)
Home-page: https://github.com/faebstn96/trainable-bilateral-filter-source
Author: Fabian Wagner
Author-email: fabian.wagner@fau.de
License: UNKNOWN
Platform: UNKNOWN
